symspellpy_ko/__init__.py
symspellpy_ko/helper.py
symspellpy_ko/symspell.py
symspellpy_ko/unicode.py
symspellpy_ko/res/__init__.py
symspellpy_ko/res/ko_50k.txt
symspellpy_ko/res/ko_50k_d.txt
symspellpy_ko/res/ko_bigrams_1M.txt
symspellpy_ko/res/ko_bigrams_1M_d.txt
symspellpy_ko-0.1.4.dist-info/LICENSE
symspellpy_ko-0.1.4.dist-info/METADATA
symspellpy_ko-0.1.4.dist-info/WHEEL
symspellpy_ko-0.1.4.dist-info/top_level.txt
symspellpy_ko-0.1.4.dist-info/RECORD
